rvv/__init__.py
rvv/base.py
rvv/extensions/ZVFH.py
rvv/extensions/__init__.py
rvv/extensions/extensions.py
rvv/functions/__init__.py
rvv/functions/bitwise/__init__.py
rvv/functions/bitwise/logical.py
rvv/functions/bitwise/shift.py
rvv/functions/conversion/__init__.py
rvv/functions/conversion/conversion.py
rvv/functions/fixedpoint/__init__.py
rvv/functions/fixedpoint/fixedpoint.py
rvv/functions/float/__init__.py
rvv/functions/float/fcompare.py
rvv/functions/float/fmisc.py
rvv/functions/float/fmuladd.py
rvv/functions/float/fopsbasic.py
rvv/functions/float/fwiden.py
rvv/functions/fold/__init__.py
rvv/functions/fold/foldmisc.py
rvv/functions/fold/foldsum.py
rvv/functions/initialize/__init__.py
rvv/functions/initialize/initialize.py
rvv/functions/integer/__init__.py
rvv/functions/integer/add.py
rvv/functions/integer/carry.py
rvv/functions/integer/compare.py
rvv/functions/integer/divide.py
rvv/functions/integer/misc.py
rvv/functions/integer/muladd.py
rvv/functions/integer/multiply.py
rvv/functions/integer/subtract.py
rvv/functions/mask/__init__.py
rvv/functions/mask/logical.py
rvv/functions/mask/mmisc.py
rvv/functions/memory/__init__.py
rvv/functions/memory/indexed.py
rvv/functions/memory/loadstore.py
rvv/functions/memory/segmented.py
rvv/functions/permutation/__init__.py
rvv/functions/permutation/permutation.py
rvv/utils/__init__.py
rvv/utils/sew.py
rvv-0.1.0.dist-info/METADATA
rvv-0.1.0.dist-info/WHEEL
rvv-0.1.0.dist-info/top_level.txt
rvv-0.1.0.dist-info/RECORD
