Metadata-Version: 2.2
Name: rvv
Version: 0.1.0
Summary: A library for RISC-V Vector extensions
Home-page: https://github.com/OM3R-Nazir/rvv.git
Author: Omer Nazir
License: MIT
Classifier: Programming Language :: Python :: 3
Classifier: License :: OSI Approved :: MIT License
Classifier: Operating System :: OS Independent
Requires-Python: >=3.7
Requires-Dist: numpy>=1.18
Dynamic: author
Dynamic: classifier
Dynamic: description
Dynamic: description-content-type
Dynamic: home-page
Dynamic: license
Dynamic: requires-dist
Dynamic: requires-python
Dynamic: summary
